countrytagger/__init__.py
countrytagger/generate.py
countrytagger/util.py
countrytagger/data/places.csv
countrytagger-0.1.2.dist-info/LICENSE
countrytagger-0.1.2.dist-info/METADATA
countrytagger-0.1.2.dist-info/WHEEL
countrytagger-0.1.2.dist-info/top_level.txt
countrytagger-0.1.2.dist-info/RECORD
