Metadata-Version: 2.1
Name: countrytagger
Version: 0.1.2
Summary: Tag the names of countries and in text.
Home-page: https://github.com/alephdata/countrytagger
Author: OCCRP
License: MIT
Platform: UNKNOWN
Requires-Dist: normality (>=2.0.0)
Requires-Dist: pyahocorasick (>=1.4.0)
